odoo/addons/crm_team_parent/README.rst
odoo/addons/crm_team_parent/__init__.py
odoo/addons/crm_team_parent/__manifest__.py
odoo/addons/crm_team_parent/i18n/crm_team_parent.pot
odoo/addons/crm_team_parent/models/__init__.py
odoo/addons/crm_team_parent/models/crm_team.py
odoo/addons/crm_team_parent/readme/CONTRIBUTORS.rst
odoo/addons/crm_team_parent/readme/DESCRIPTION.rst
odoo/addons/crm_team_parent/readme/USAGE.rst
odoo/addons/crm_team_parent/static/description/icon.png
odoo/addons/crm_team_parent/static/description/index.html
odoo/addons/crm_team_parent/tests/__init__.py
odoo/addons/crm_team_parent/tests/test_crm_team_parent.py
odoo/addons/crm_team_parent/views/crm_team.xml
odoo12_addon_crm_team_parent-12.0.1.0.1.dist-info/METADATA
odoo12_addon_crm_team_parent-12.0.1.0.1.dist-info/WHEEL
odoo12_addon_crm_team_parent-12.0.1.0.1.dist-info/top_level.txt
odoo12_addon_crm_team_parent-12.0.1.0.1.dist-info/RECORD
